lucidity/__init__.py
lucidity/__main__.py
lucidity/context.py
lucidity/log.py
lucidity/prompts.py
lucidity/server.py
lucidity/tools/__init__.py
lucidity/tools/code_analysis.py
mseep_lucidity_mcp-0.1.2.dist-info/METADATA
mseep_lucidity_mcp-0.1.2.dist-info/WHEEL
mseep_lucidity_mcp-0.1.2.dist-info/entry_points.txt
mseep_lucidity_mcp-0.1.2.dist-info/licenses/LICENSE
mseep_lucidity_mcp-0.1.2.dist-info/RECORD
