Metadata-Version: 2.4
Name: mseep-lucidity-mcp
Version: 0.1.2
Summary: An AI powered code review tool for MCP
Project-URL: Homepage, https://github.com/hyperbliss/lucidity
Project-URL: Issues, https://github.com/hyperbliss/lucidity/issues
Project-URL: Documentation, https://github.com/hyperbliss/lucidity#readme
Author-email: mseep <support@skydeck.ai>
License:                                  Apache License
License-File: LICENSE
Keywords: ai,android,claude,llm,mcp
Classifier: Development Status :: 4 - Beta
Classifier: Intended Audience :: Developers
Classifier: License :: OSI Approved :: Apache Software License
Classifier: Programming Language :: Python :: 3
Classifier: Programming Language :: Python :: 3.13
Requires-Python: >=3.13
Requires-Dist: anyio>=4.8.0
Requires-Dist: dotenv>=0.9.9
Requires-Dist: httpx>=0.28.1
Requires-Dist: mcp[cli]>=1.4.1
Requires-Dist: rich>=13.9.4
Requires-Dist: sse-starlette>=2.2.1
Requires-Dist: starlette>=0.36.3
Requires-Dist: types-colorama>=0.4.15.20240311
Requires-Dist: types-pexpect>=4.9.0.20241208
Requires-Dist: types-pygments>=2.19.0.20250305
Requires-Dist: types-pyyaml>=6.0.12.20241230
Requires-Dist: types-setuptools>=76.0.0.20250313
Requires-Dist: uvicorn>=0.30.0
